frigid/__init__.py
frigid/classes.py
frigid/dictionaries.py
frigid/exceptions.py
frigid/installers.py
frigid/modules.py
frigid/namespaces.py
frigid/py.typed
frigid/sequences.py
frigid/__/__init__.py
frigid/__/dictionaries.py
frigid/__/doctab.py
frigid/__/exceptions.py
frigid/__/imports.py
frigid/__/nomina.py
frigid/_typedecls/__builtins__.pyi
frigid-4.2.dist-info/METADATA
frigid-4.2.dist-info/WHEEL
frigid-4.2.dist-info/licenses/LICENSE.txt
frigid-4.2.dist-info/RECORD
