Metadata-Version: 2.4
Name: frigid
Version: 4.2
Summary: Immutable data structures.
Project-URL: Homepage, https://github.com/emcd/python-frigid
Project-URL: Documentation, https://emcd.github.io/python-frigid
Project-URL: Download, https://pypi.org/project/frigid/#files
Project-URL: Source Code, https://github.com/emcd/python-frigid
Project-URL: Issue Tracker, https://github.com/emcd/python-frigid/issues
Author-email: Eric McDonald <emcd@users.noreply.github.com>
License-Expression: Apache-2.0
License-File: LICENSE.txt
Keywords: api,dictionary,immutability,immutable,namespace
Classifier: Development Status :: 5 - Production/Stable
Classifier: Intended Audience :: Developers
Classifier: License :: OSI Approved :: Apache Software License
Classifier: Programming Language :: Python :: 3 :: Only
Classifier: Programming Language :: Python :: 3.10
Classifier: Programming Language :: Python :: 3.11
Classifier: Programming Language :: Python :: 3.12
Classifier: Programming Language :: Python :: 3.13
Classifier: Programming Language :: Python :: Implementation :: CPython
Classifier: Programming Language :: Python :: Implementation :: PyPy
Classifier: Topic :: Software Development
Requires-Python: >=3.10
Requires-Dist: absence~=1.1
Requires-Dist: classcore~=1.4
Requires-Dist: dynadoc~=1.2
Requires-Dist: typing-extensions
